flexiblenn/ActivationFunctions.py
flexiblenn/HiddenNode.py
flexiblenn/InputNode.py
flexiblenn/NeuralNet.py
flexiblenn/OutputNode.py
flexiblenn/__init__.py
flexible_neural_network-0.0.42.dist-info/METADATA
flexible_neural_network-0.0.42.dist-info/WHEEL
flexible_neural_network-0.0.42.dist-info/top_level.txt
flexible_neural_network-0.0.42.dist-info/RECORD
